pathfind_visualiser/__init__.py
pathfind_visualiser/algorithms.py
pathfind_visualiser/board.py
pathfind_visualiser/buttons.py
pathfind_visualiser/dropdown.py
pathfind_visualiser/main.py
pathfind_visualiser/maze.py
pathfind_visualiser-0.1.3.dist-info/entry_points.txt
pathfind_visualiser-0.1.3.dist-info/LICENSE
pathfind_visualiser-0.1.3.dist-info/WHEEL
pathfind_visualiser-0.1.3.dist-info/METADATA
pathfind_visualiser-0.1.3.dist-info/RECORD
