Metadata-Version: 2.1
Name: pathfind-visualiser
Version: 0.1.3
Summary: Pathfinding algorigthms written in Python and visualised with the Pygame library
Home-page: https://github.com/Rolv-Apneseth/pathfind-visualiser
License: MIT
Author: Rolv-Apneseth
Author-email: rolv.apneseth@gmail.com
Requires-Python: >=3.9,<4.0.0
Classifier: License :: OSI Approved :: MIT License
Classifier: Programming Language :: Python :: 3
Classifier: Programming Language :: Python :: 3.10
Classifier: Programming Language :: Python :: 3.9
Requires-Dist: pygame (>=2.1.2,<3.0.0)
